{"batchcomplete":"","warnings":{"main":{"*":"Subscribe to the mediawiki-api-announce mailing list at <https://lists.wikimedia.org/postorius/lists/mediawiki-api-announce.lists.wikimedia.org/> for notice of API deprecations and breaking changes. Use [[Special:ApiFeatureUsage]] to see usage of deprecated features by your application."},"revisions":{"*":"Because \"rvslots\" was not specified, a legacy format has been used for the output. This format is deprecated, and in the future the new format will always be used."},"extracts":{"*":"HTML may be malformed and/or unbalanced and may omit inline images. Use at your own risk. Known problems are listed at https://www.mediawiki.org/wiki/Special:MyLanguage/Extension:TextExtracts#Caveats."}},"query":{"pages":{"2237850":{"pageid":2237850,"ns":0,"title":"\u733f\u5ca1\u5c71\u57ce","extract":"<p><b>\u733f\u5ca1\u5c71\u57ce</b>\uff08\u3055\u308b\u304a\u304b\u3084\u307e\u3058\u3087\u3046\uff09\u306f\u3001\u7d00\u4f0a\u56fd\uff08\u73fe\u30fb\u548c\u6b4c\u5c71\u770c\u7d00\u306e\u5ddd\u5e02\u7c89\u6cb3\uff09\u306b\u3042\u3063\u305f\u65e5\u672c\u306e\u57ce\u3002\u5225\u540d\u3001\u7c89\u6cb3\u57ce\u3002\n</p>\n<h2><span id=\".E6.A6.82.E8.A6.81\"></span><span id=\"\u6982\u8981\">\u6982\u8981</span></h2>\n<p>1573\u5e74\uff08\u5929\u6b63\u5143\u5e74\uff09\u3001\u6839\u6765\u5bfa\u3068\u4e26\u3093\u3067\u7d00\u30ce\u5ddd\u6d41\u57df\u306b\u52e2\u529b\u304c\u3042\u3063\u305f\u7c89\u6cb3\u5bfa\u304c\u5bfa\u306e\u9632\u885b\u306e\u305f\u3081\u306b\u5883\u5185\u5357\u5074\u306e\u733f\u5ca1\u5c71\uff08\u73fe\u30fb\u79cb\u8449\u5c71\uff09\u306b\u7bc9\u57ce\u30021585\u5e74\uff08\u5929\u6b6313\u5e74\uff09\u306e\u7d00\u5dde\u5f81\u4f10\u306e\u5f8c\u3001\u7d00\u4f0a\u56fd\u7c89\u6cb3\u306b\u5c01\u3058\u3089\u308c\u305f\u85e4\u5802\u9ad8\u864e\u304c\u7c89\u6cb3\u5bfa\u3092\u727d\u5236\u3059\u308b\u305f\u3081\u306b\u5165\u57ce\u3057\u3001\u6539\u7bc9\u3057\u305f\u3002\u5c71\u57ce\u3067\u5357\u5074\u306b\u6d41\u308c\u308b\u4e2d\u6d25\u5ddd\u3092\u5800\u3068\u3057\u3066\u4ee3\u7528\u3057\u305f\u57ce\u3067\u3001\u9ad8\u864e\u304c\u4f0a\u4e88\u56fd\u5b87\u548c\u5cf6\u306b\u79fb\u5c01\u3055\u308c\u305f\u5f8c\u3001\u5ec3\u57ce\u3068\u306a\u308b\u3002\u96a3\u63a5\u3059\u308b\u7c89\u6cb3\u5bfa\u3092\u4e00\u671b\u3067\u304d\u308b\u3002\n</p><p>\u73fe\u5728\u306f\u79cb\u8449\u516c\u5712\u3068\u3057\u3066\u6574\u5099\u3055\u308c\u3001\u66f2\u8f2a\u306e\u307f\u304c\u6b8b\u3055\u308c\u3066\u3044\u308b\u3002\u516c\u5712\u5185\u306b\u57ce\u8de1\u3092\u793a\u3059\u77f3\u7891\u3068\u8aac\u660e\u6587\u304c\u3042\u308b\u3002\n</p>\n<h2><span id=\".E9.96.A2.E9.80.A3.E9.A0.85.E7.9B.AE\"></span><span id=\"\u95a2\u9023\u9805\u76ee\">\u95a2\u9023\u9805\u76ee</span></h2>\n<ul><li>\u65e5\u672c\u306e\u57ce\u4e00\u89a7</li>\n<li>\u548c\u6b4c\u5c71\u770c\u306e\u57ce\u4e00\u89a7</li></ul><!-- \nNewPP limit report\nParsed by mw\u2010api\u2010ext.codfw.main\u20105fbf47b6b\u201086n6t\nCached time: 20240114112607\nCache expiry: 2592000\nReduced expiry: false\nComplications: []\nCPU time usage: 0.047 seconds\nReal time usage: 0.068 seconds\nPreprocessor visited node count: 200/1000000\nPost\u2010expand include size: 6089/2097152 bytes\nTemplate argument size: 116/2097152 bytes\nHighest expansion depth: 6/100\nExpensive parser function count: 0/500\nUnstrip recursion depth: 0/20\nUnstrip post\u2010expand size: 0/5000000 bytes\nLua time usage: 0.006/10.000 seconds\nLua memory usage: 754123/52428800 bytes\nNumber of Wikibase entities loaded: 0/400\n--><!--\nTransclusion expansion time report (%,ms,calls,template)\n100.00%   29.844      1 -total\n100.00%   29.844      1 Template:\u65e5\u672c\u306e\u57ce\u90ed\u6982\u8981\u8868\n 89.04%   26.572      1 Template:Infobox\n-->","revisions":[{"contentformat":"text/x-wiki","contentmodel":"wikitext","*":"{{\u65e5\u672c\u306e\u57ce\u90ed\u6982\u8981\u8868\n|img =\u30d5\u30a1\u30a4\u30eb:Saruokayama_castleOct2018.JPG \n|img_capt = \n|img_width = \n|name = \u733f\u5ca1\u5c71\u57ce\n|pref = \u548c\u6b4c\u5c71\u770c\n|ar_called = \n|struct = \u5c71\u57ce\n|tower_struct = \n|builders = \n|build_y = 1573\u5e74\n|revamp = \u85e4\u5802\u9ad8\u864e\n|rulers = \u85e4\u5802\u9ad8\u864e\n|reject_y = 1596\u5e74\n|remains = \u66f2\u8f2a\n|location = \n}}\n\n'''\u733f\u5ca1\u5c71\u57ce'''\uff08\u3055\u308b\u304a\u304b\u3084\u307e\u3058\u3087\u3046\uff09\u306f\u3001[[\u7d00\u4f0a\u56fd]]\uff08\u73fe\u30fb[[\u548c\u6b4c\u5c71\u770c]][[\u7d00\u306e\u5ddd\u5e02]]\u7c89\u6cb3\uff09\u306b\u3042\u3063\u305f[[\u65e5\u672c\u306e\u57ce]]\u3002\u5225\u540d\u3001\u7c89\u6cb3\u57ce\u3002\n\n== \u6982\u8981 ==\n[[1573\u5e74]]\uff08[[\u5929\u6b63]]\u5143\u5e74\uff09\u3001[[\u6839\u6765\u5bfa]]\u3068\u4e26\u3093\u3067[[\u7d00\u30ce\u5ddd]]\u6d41\u57df\u306b\u52e2\u529b\u304c\u3042\u3063\u305f[[\u7c89\u6cb3\u5bfa]]\u304c\u5bfa\u306e\u9632\u885b\u306e\u305f\u3081\u306b\u5883\u5185\u5357\u5074\u306e\u733f\u5ca1\u5c71\uff08\u73fe\u30fb\u79cb\u8449\u5c71\uff09\u306b\u7bc9\u57ce\u3002[[1585\u5e74]]\uff08\u5929\u6b6313\u5e74\uff09\u306e[[\u7d00\u5dde\u5f81\u4f10]]\u306e\u5f8c\u3001\u7d00\u4f0a\u56fd\u7c89\u6cb3\u306b\u5c01\u3058\u3089\u308c\u305f[[\u85e4\u5802\u9ad8\u864e]]\u304c\u7c89\u6cb3\u5bfa\u3092\u727d\u5236\u3059\u308b\u305f\u3081\u306b\u5165\u57ce\u3057\u3001\u6539\u7bc9\u3057\u305f\u3002[[\u5c71\u57ce]]\u3067\u5357\u5074\u306b\u6d41\u308c\u308b\u4e2d\u6d25\u5ddd\u3092\u5800\u3068\u3057\u3066\u4ee3\u7528\u3057\u305f\u57ce\u3067\u3001\u9ad8\u864e\u304c[[\u4f0a\u4e88\u56fd]][[\u5b87\u548c\u5cf6\u57ce|\u5b87\u548c\u5cf6]]\u306b\u79fb\u5c01\u3055\u308c\u305f\u5f8c\u3001\u5ec3\u57ce\u3068\u306a\u308b\u3002\u96a3\u63a5\u3059\u308b\u7c89\u6cb3\u5bfa\u3092\u4e00\u671b\u3067\u304d\u308b\u3002\n\n\u73fe\u5728\u306f\u79cb\u8449\u516c\u5712\u3068\u3057\u3066\u6574\u5099\u3055\u308c\u3001[[\u66f2\u8f2a]]\u306e\u307f\u304c\u6b8b\u3055\u308c\u3066\u3044\u308b\u3002\u516c\u5712\u5185\u306b\u57ce\u8de1\u3092\u793a\u3059\u77f3\u7891\u3068\u8aac\u660e\u6587\u304c\u3042\u308b\u3002\n\n== \u95a2\u9023\u9805\u76ee ==\n*[[\u65e5\u672c\u306e\u57ce\u4e00\u89a7]]\n*[[\u548c\u6b4c\u5c71\u770c\u306e\u57ce\u4e00\u89a7]]\n\n{{\u30c7\u30d5\u30a9\u30eb\u30c8\u30bd\u30fc\u30c8:\u3055\u308b\u304a\u304b\u3084\u307e\u3057\u3088\u3046}}\n[[Category:\u548c\u6b4c\u5c71\u770c\u306e\u57ce]]\n[[Category:\u73fe\u5b58\u3057\u306a\u3044\u548c\u6b4c\u5c71\u770c\u306e\u5efa\u7bc9\u7269]]\n[[Category:\u7d00\u306e\u5ddd\u5e02\u306e\u5efa\u7bc9\u7269|\u5ec3\u3055\u308b\u304a\u304b\u3084\u307e\u3057\u3088\u3046]]\n[[Category:\u7d00\u306e\u5ddd\u5e02\u306e\u6b74\u53f2]]\n[[Category:\u7d00\u4f0a\u56fd\u306e\u57ce]]"}],"thumbnail":{"source":"https://upload.wikimedia.org/wikipedia/commons/thumb/e/e7/Saruokayama_castleOct2018.JPG/50px-Saruokayama_castleOct2018.JPG","width":50,"height":33},"pageimage":"Saruokayama_castleOct2018.JPG"}}}}